motrack_motion/__init__.py
motrack_motion/version.py
motrack_motion/common/__init__.py
motrack_motion/common/conventions.py
motrack_motion/common/formats.py
motrack_motion/common/project.py
motrack_motion/config_parser/__init__.py
motrack_motion/config_parser/core.py
motrack_motion/datasets/__init__.py
motrack_motion/datasets/factory.py
motrack_motion/datasets/utils.py
motrack_motion/datasets/augmentations/__init__.py
motrack_motion/datasets/augmentations/trajectory.py
motrack_motion/datasets/common/__init__.py
motrack_motion/datasets/common/scene_info.py
motrack_motion/datasets/mot/__init__.py
motrack_motion/datasets/mot/core.py
motrack_motion/datasets/mot/tools/__init__.py
motrack_motion/datasets/mot/tools/run_split_train_into_two_halves.py
motrack_motion/datasets/tools/__init__.py
motrack_motion/datasets/tools/run_calc_dataset_stats.py
motrack_motion/datasets/torch/__init__.py
motrack_motion/datasets/torch/core.py
motrack_motion/datasets/transforms/__init__.py
motrack_motion/datasets/transforms/base.py
motrack_motion/datasets/transforms/bbox.py
motrack_motion/datasets/transforms/factory.py
motrack_motion/filter/__init__.py
motrack_motion/filter/base.py
motrack_motion/filter/buffer.py
motrack_motion/filter/end_to_end_filter.py
motrack_motion/filter/factory.py
motrack_motion/filter/transfilter.py
motrack_motion/library/__init__.py
motrack_motion/library/building_blocks/__init__.py
motrack_motion/library/building_blocks/attention.py
motrack_motion/library/building_blocks/mlp.py
motrack_motion/library/cv/__init__.py
motrack_motion/library/cv/bbox.py
motrack_motion/library/numpy_utils/__init__.py
motrack_motion/library/numpy_utils/bbox.py
motrack_motion/library/numpy_utils/io.py
motrack_motion/library/time_series/__init__.py
motrack_motion/library/time_series/transform.py
motrack_motion/models/__init__.py
motrack_motion/models/architectures/__init__.py
motrack_motion/models/architectures/end_to_end.py
motrack_motion/models/architectures/factory.py
motrack_motion-0.2.4.dist-info/LICENSE
motrack_motion-0.2.4.dist-info/METADATA
motrack_motion-0.2.4.dist-info/WHEEL
motrack_motion-0.2.4.dist-info/top_level.txt
motrack_motion-0.2.4.dist-info/RECORD
